{
    "redirect-rules": [
        {
            "src": "//(:?acg\\.tv|b23\\.tv|b23\\.wtf|bili2233\\.cn)/av",
            "kind": "wildcard",
            "dst": "//www.bilibili.com/video/av",
            "enable": true
        },
        {
            "src": "//b23.tv",
            "kind": "wildcard",
            "dst": "//b23.wtf",
            "enable": true
        },
        {
            "src": "//acg.tv/sm",
            "kind": "wildcard",
            "dst": "//www.nicovideo.jp/watch/sm",
            "enable": true
        },
        {
            "src": "//nico.ms/sm",
            "kind": "wildcard",
            "dst": "//www.nicovideo.jp/watch/sm",
            "enable": true
        },
        {
            "src": "//nico.ms/nm",
            "kind": "wildcard",
            "dst": "//www.nicovideo.jp/watch/nm",
            "enable": true
        },
        {
            "src": "//nico.ms/im",
            "kind": "wildcard",
            "dst": "//seiga.nicovideo.jp/seiga/im",
            "enable": true
        }
    ]
}